captiv/__init__.py
captiv/__main__.py
captiv/api/__init__.py
captiv/api/server.py
captiv/cli/__init__.py
captiv/cli/__main__.py
captiv/cli/commands/__init__.py
captiv/cli/commands/caption/__init__.py
captiv/cli/commands/caption/clear.py
captiv/cli/commands/caption/generate.py
captiv/cli/commands/caption/get.py
captiv/cli/commands/caption/list.py
captiv/cli/commands/caption/set.py
captiv/cli/commands/caption/unset.py
captiv/cli/commands/config/__init__.py
captiv/cli/commands/config/clear.py
captiv/cli/commands/config/get.py
captiv/cli/commands/config/list.py
captiv/cli/commands/config/set.py
captiv/cli/commands/config/unset.py
captiv/cli/commands/gui/__init__.py
captiv/cli/commands/gui/launch.py
captiv/cli/commands/model/__init__.py
captiv/cli/commands/model/list.py
captiv/cli/commands/model/show.py
captiv/cli/commands/runpod/__init__.py
captiv/cli/commands/runpod/create.py
captiv/cli/commands/runpod/gpu_types.py
captiv/cli/commands/runpod/list.py
captiv/cli/commands/runpod/status.py
captiv/cli/commands/runpod/stop.py
captiv/cli/commands/runpod/terminate.py
captiv/cli/error_handling.py
captiv/cli/options.py
captiv/config/__init__.py
captiv/config/config.py
captiv/config/config_section.py
captiv/config/defaults/__init__.py
captiv/config/defaults/generation_defaults.py
captiv/config/defaults/gui_defaults.py
captiv/config/defaults/model_defaults.py
captiv/config/defaults/runpod_defaults.py
captiv/config/defaults/system_defaults.py
captiv/gui/__init__.py
captiv/gui/__main__.py
captiv/gui/logging.py
captiv/gui/main.py
captiv/gui/sections/__init__.py
captiv/gui/sections/bulk_caption.py
captiv/gui/sections/caption.py
captiv/gui/sections/directory.py
captiv/gui/sections/gallery.py
captiv/gui/sections/model.py
captiv/gui/styles.py
captiv/gui/utils.py
captiv/models/__init__.py
captiv/models/base_model.py
captiv/models/blip2_model.py
captiv/models/blip_model.py
captiv/models/joycaption_model.py
captiv/models/kosmos_model.py
captiv/models/vit_gpt2_model.py
captiv-0.1.13.dist-info/METADATA
captiv-0.1.13.dist-info/WHEEL
captiv-0.1.13.dist-info/entry_points.txt
captiv-0.1.13.dist-info/RECORD
