Metadata-Version: 2.3
Name: captiv
Version: 0.1.13
Summary: Image captioning tool with CLI and GUI interfaces
License: MIT
Author: Andy Hite
Author-email: andy@andyhite.com
Requires-Python: >=3.12,<4.0.0
Classifier: License :: OSI Approved :: MIT License
Classifier: Programming Language :: Python :: 3
Classifier: Programming Language :: Python :: 3.12
Classifier: Programming Language :: Python :: 3.13
Provides-Extra: joycaption
Requires-Dist: Pillow (>=10.0.0,<11.0.0)
Requires-Dist: accelerate (>=0.30.0) ; extra == "joycaption"
Requires-Dist: audioop-lts (>=0.2.1,<0.3.0) ; python_version >= "3.13"
Requires-Dist: click (>=8.1.7,<9.0.0)
Requires-Dist: fastapi (>=0.115.2,<1.0.0)
Requires-Dist: gradio (>=4.44.0,<6.0.0)
Requires-Dist: jinja2 (>=3.1.2,<4.0.0)
Requires-Dist: loguru (>=0.7.2,<0.8.0)
Requires-Dist: psutil (>=5.9.0,<6.0.0)
Requires-Dist: python-multipart (>=0.0.9)
Requires-Dist: requests (>=2.31.0,<3.0.0)
Requires-Dist: rich (>=12.6.0,<13.0.0)
Requires-Dist: runpod (>=1.7.0,<2.0.0)
Requires-Dist: toml (>=0.10.2,<0.11.0)
Requires-Dist: tomlkit (>=0.12.2)
Requires-Dist: torch (>=2.7.0,<3.0.0)
Requires-Dist: transformers (>=4.51.3,<5.0.0)
Requires-Dist: typer[all] (>=0.9.0,<1.0.0)
Requires-Dist: typing-extensions (>=4.7.0,<5.0.0)
Requires-Dist: uvicorn (>=0.23.2,<0.24.0)
Project-URL: Repository, https://github.com/andyhite/captiv
